updowncounter.v
`timescale 1ns/1ps

module updowncounter(
	input	wire	clk,
	input	wire	mode,
	input	wire	rst,
	output	reg	signed	[3:0]	val
);

wire	signed	[3:0]	next_val;

always @(posedge clk)
	if(rst)	val <= 4'sd0;
	else val	<= next_val;

assign	next_val	=	mode ? (val + 1'b1) : (val - 1'b1);

endmodule

module	tb;

	reg	clk;
	reg	mode;
	reg	rst;
	wire	signed	[3:0]	val;

	updowncounter u0(.clk(clk), .mode(mode), .rst(rst), .val(val));

	initial begin
	clk = 1'b0;
	forever #10 clk = ~clk;

	end

	initial begin
	rst = 1'b0;
	#13
	rst = 1'b1;
	#20
	rst = 1'b0;

	end

	initial begin
			mode = 1'b1;
		end

	initial begin
		$monitor("%d  ||||  %b", val, val);
	end

	initial begin
		$dumpfile("updowncounter.vcd");
		$dumpvars;
		#500
		$finish;
	end

	endmodule

updowncounter.vcd
$date
	Wed Jun 21 16:42:56 2023
$end
$version
	Icarus Verilog
$end
$timescale
	1ps
$end
$scope module tb $end
$var wire 4 ! val [3:0] $end
$var reg 1 " clk $end
$var reg 1 # mode $end
$var reg 1 $ rst $end
$scope module u0 $end
$var wire 1 " clk $end
$var wire 1 # mode $end
$var wire 1 $ rst $end
$var wire 4 % next_val [3:0] $end
$var reg 4 & val [3:0] $end
$upscope $end
$upscope $end
$enddefinitions $end
#0
$dumpvars
bx &
bx %
0$
1#
0"
bx !
$end
#10000
1"
#13000
1$
#20000
0"
#30000
b1 %
b0 !
b0 &
1"
#33000
0$
#40000
0"
#50000
b10 %
b1 !
b1 &
1"
#60000
0"
#70000
b11 %
b10 !
b10 &
1"
#80000
0"
#90000
b100 %
b11 !
b11 &
1"
#100000
0"
#110000
b101 %
b100 !
b100 &
1"
#120000
0"
#130000
b110 %
b101 !
b101 &
1"
#140000
0"
#150000
b111 %
b110 !
b110 &
1"
#160000
0"
#170000
b1000 %
b111 !
b111 &
1"
#180000
0"
#190000
b1001 %
b1000 !
b1000 &
1"
#200000
0"
#210000
b1010 %
b1001 !
b1001 &
1"
#220000
0"
#230000
b1011 %
b1010 !
b1010 &
1"
#240000
0"
#250000
b1100 %
b1011 !
b1011 &
1"
#260000
0"
#270000
b1101 %
b1100 !
b1100 &
1"
#280000
0"
#290000
b1110 %
b1101 !
b1101 &
1"
#300000
0"
#310000
b1111 %
b1110 !
b1110 &
1"
#320000
0"
#330000
b0 %
b1111 !
b1111 &
1"
#340000
0"
#350000
b1 %
b0 !
b0 &
1"
#360000
0"
#370000
b10 %
b1 !
b1 &
1"
#380000
0"
#390000
b11 %
b10 !
b10 &
1"
#400000
0"
#410000
b100 %
b11 !
b11 &
1"
#420000
0"
#430000
b101 %
b100 !
b100 &
1"
#440000
0"
#450000
b110 %
b101 !
b101 &
1"
#460000
0"
#470000
b111 %
b110 !
b110 &
1"
#480000
0"
#490000
b1000 %
b111 !
b111 &
1"
