VerilogHDL/delay_SRlatch/delay_SRlatch.v
module SRlatch(

input	set, reset,
output	q, qbar
);

nand	#(1)	n1(q, reset, qbar);	// Delay of 1 on gate n1
nand	#(1)	n2(qbar, set, q);	// Delay of 1 on gate n2

endmodule

//TEST BENCH
module tb;

reg	SET, RST;
wire	Q, QBAR;


SRlatch	Latch1(.set(SET), .reset(RST), .q(Q), .qbar(QBAR));

initial begin
// 1 cycle
SET = 1'b0; RST = 1'b0;
#5
SET = 1'b0; RST = 1'b1;
#5
SET = 1'b1; RST = 1'b0;
#5
SET = 1'b1; RST = 1'b1;
// 2 cycle
SET = 1'b0; RST = 1'b0;
#5
SET = 1'b0; RST = 1'b1;
#5
SET = 1'b1; RST = 1'b0;
#5
SET = 1'b1; RST = 1'b1;
#10
$finish;

end

initial begin
$dumpfile("delay_SRlatch.vcd");
$dumpvars;

end

endmodule

VerilogHDL/delay_SRlatch/delay_SRlatch.vcd
$date
	Fri Aug 18 15:06:29 2023
$end
$version
	Icarus Verilog
$end
$timescale
	1s
$end
$scope module tb $end
$var wire 1 ! QBAR $end
$var wire 1 " Q $end
$var reg 1 # RST $end
$var reg 1 $ SET $end
$scope module Latch1 $end
$var wire 1 " q $end
$var wire 1 ! qbar $end
$var wire 1 # reset $end
$var wire 1 $ set $end
$upscope $end
$upscope $end
$enddefinitions $end
#0
$dumpvars
0$
0#
x"
x!
$end
#1
1!
1"
#5
1#
#6
0"
#10
0#
1$
#11
1"
#12
0!
#15
0$
0#
#16
1!
#20
1#
#21
0"
#25
0#
1$
#26
1"
#27
0!
#30
1#
