VerilogHDL/delay/delay.v
module	D(
input	a, b, c,
output	out
);

wire	e;

and	#(5) a1(e, a, b);
or	#(4) o1(out, e, c);

endmodule

module	tb;

reg	A, B, C;
wire	Output;

D	D1(
	.a(A),
	.b(B),
	.c(C),
	.out(Output)
	);

initial	begin

A = 1'b0; B = 1'b0; C = 1'b0;
#10
A = 1'b1; B = 1'b1; C = 1'b1;
#10
A = 1'b1; B = 1'b0; C = 1'b0;
#10
$finish;

end

initial begin
$dumpfile("delay.vcd");
$dumpvars;
end


endmodule

VerilogHDL/delay/delay.vcd
$date
	Thu Aug 17 18:35:23 2023
$end
$version
	Icarus Verilog
$end
$timescale
	1s
$end
$scope module tb $end
$var wire 1 ! Output $end
$var reg 1 " A $end
$var reg 1 # B $end
$var reg 1 $ C $end
$scope module D1 $end
$var wire 1 " a $end
$var wire 1 # b $end
$var wire 1 $ c $end
$var wire 1 % e $end
$var wire 1 ! out $end
$upscope $end
$upscope $end
$enddefinitions $end
#0
$dumpvars
x%
0$
0#
0"
x!
$end
#5
0%
#9
0!
#10
1$
1#
1"
#14
1!
#15
1%
#20
0$
0#
#25
0%
#29
0!
