LAB4/Counter.v
module	counter4(

	input	wire	clk,
	input	wire	en,
	input	wire	nclear,
	output	wire	[3:0]	q

);

wire	en0,en1,en2,en3;

t_ff u0(.clk(clk), .nclear(nclear), .en(en0), .q(q[0]));
t_ff u1(.clk(clk), .nclear(nclear), .en(en1), .q(q[1]));
t_ff u2(.clk(clk), .nclear(nclear), .en(en2), .q(q[2]));
t_ff u3(.clk(clk), .nclear(nclear), .en(en3), .q(q[3]));

assign	en0 = 			en;
assign	en1	=	en0	& q[0];
assign	en2	=	en1	& q[1];
assign	en3	=	en2	& q[2];


endmodule



module	t_ff(
	input	wire	clk,
	input	wire	en,
	input	wire	nclear,
	output	reg		q
);

always @(posedge clk)
	if(~nclear) q <= 1'b0;
	else if(en) q <= ~q;

endmodule


module tb; // TEST BENCH

reg clk;
reg en;
reg nclear;
wire [3:0] q;


counter4 u0(.clk(clk), .en(en), .nclear(nclear), .q(q));

initial begin
	clk	=	1'b0;
	forever	#10 clk	=	~clk;
end

initial begin
	nclear	=	1'b1;
	#12
	nclear	=	1'b0;
	#20
	nclear	=	1'b1;
end


initial begin
	en	=	1'b0;
	#40
	en	=	1'b1;
end

initial	begin
	$monitor("%d", q);
end

initial begin

	$dumpfile("counter.vcd");
	$dumpvars;
	#200
	$finish;
	end


	endmodule

LAB4/counter4.vcd
$date
	Thu Jun 22 14:44:44 2023
$end
$version
	Icarus Verilog
$end
$timescale
	1s
$end
$scope module tb $end
$var wire 4 ! q [3:0] $end
$var reg 1 " clk $end
$var reg 1 # en $end
$var reg 1 $ nclear $end
$scope module u0 $end
$var wire 1 " clk $end
$var wire 1 # en $end
$var wire 1 % en0 $end
$var wire 1 & en1 $end
$var wire 1 ' en2 $end
$var wire 1 ( en3 $end
$var wire 1 $ nclear $end
$var wire 4 ) q [3:0] $end
$scope module u0 $end
$var wire 1 " clk $end
$var wire 1 % en $end
$var wire 1 $ nclear $end
$var reg 1 * q $end
$upscope $end
$scope module u1 $end
$var wire 1 " clk $end
$var wire 1 & en $end
$var wire 1 $ nclear $end
$var reg 1 + q $end
$upscope $end
$scope module u2 $end
$var wire 1 " clk $end
$var wire 1 ' en $end
$var wire 1 $ nclear $end
$var reg 1 , q $end
$upscope $end
$scope module u3 $end
$var wire 1 " clk $end
$var wire 1 ( en $end
$var wire 1 $ nclear $end
$var reg 1 - q $end
$upscope $end
$upscope $end
$upscope $end
$enddefinitions $end
#0
$dumpvars
x-
x,
x+
x*
bx )
0(
0'
0&
0%
1$
0#
0"
bx !
$end
#10
1"
#12
0$
#20
0"
#30
0-
0,
0+
b0 !
b0 )
0*
1"
#32
1$
#40
0"
1%
1#
#50
1&
b1 !
b1 )
1*
1"
#60
0"
#70
0&
1+
b10 !
b10 )
0*
1"
#80
0"
#90
1'
1&
b11 !
b11 )
1*
1"
#100
0"
#110
0'
0&
1,
0+
b100 !
b100 )
0*
1"
#120
0"
#130
1&
b101 !
b101 )
1*
1"
#140
0"
#150
0&
1+
b110 !
b110 )
0*
1"
#160
0"
#170
1(
1'
1&
b111 !
b111 )
1*
1"
#180
0"
#190
0(
0'
0&
1-
0,
0+
b1000 !
b1000 )
0*
1"
