myproject/wallace/wallace.v

module ha( //Half Adder

input	A, B, // Input Data
output	S, C //S is Sum, C is Carry
);

assign	C = A & B; // AND operation
assign	S = A ^ B; // XOR operation

endmodule

////////////////////////////

module fa( //Full Adder

input	A, B, Cin, // Input Data
output	S, C

);


	wire	S1,S2,C1,C2;
//	wire	S, C;
// instantiation
ha	ha1(
	.A(A),
	.B(B), 
	.S(S1), 
	.C(C1));
ha	ha2(
	.A(Cin), 
	.B(S1), 
	.S(S2), 
	.C(C2));


assign	S = S2;
assign	C = C1 | C2;

endmodule


///////////////////////////////////
module TB;

reg	A,B,Cin;
wire	S,C;

fa	u0(
	.A(A), 
	.B(B), 
	.Cin(Cin), 
	.S(S), 
	.C(C));


initial begin


	A = 0; B = 0; Cin = 0; #10;
	A = 0; B = 0; Cin = 1; #10;
	A = 0; B = 1; Cin = 0; #10;
	A = 0; B = 1; Cin = 1; #10;
	A = 1; B = 0; Cin = 0; #10;
	A = 1; B = 0; Cin = 1; #10;
	A = 1; B = 1; Cin = 0; #10;
	A = 1; B = 1; Cin = 1; #10;
end

initial	begin
$display("A	|	B	|	Cin	|	S	|	C");
$monitor("%b	|	%b	|	%b	|	%b	|	%b",
	A,B,Cin,S,C);
end

initial begin

	$dumpfile("FA.vcd");
	$dumpvars;
	#100
	$finish;
	end



endmodule

myproject/wallace/FA.vcd
$date
	Thu Jul  6 11:16:52 2023
$end
$version
	Icarus Verilog
$end
$timescale
	1s
$end
$scope module TB $end
$var wire 1 ! S $end
$var wire 1 " C $end
$var reg 1 # A $end
$var reg 1 $ B $end
$var reg 1 % Cin $end
$scope module u0 $end
$var wire 1 # A $end
$var wire 1 $ B $end
$var wire 1 " C $end
$var wire 1 % Cin $end
$var wire 1 ! S $end
$var wire 1 & S2 $end
$var wire 1 ' S1 $end
$var wire 1 ( C2 $end
$var wire 1 ) C1 $end
$scope module ha1 $end
$var wire 1 # A $end
$var wire 1 $ B $end
$var wire 1 ) C $end
$var wire 1 ' S $end
$upscope $end
$scope module ha2 $end
$var wire 1 % A $end
$var wire 1 ' B $end
$var wire 1 ( C $end
$var wire 1 & S $end
$upscope $end
$upscope $end
$upscope $end
$enddefinitions $end
#0
$dumpvars
0)
0(
0'
0&
0%
0$
0#
0"
0!
$end
#10
1!
1&
1%
#20
1'
0%
1$
#30
1"
1(
0!
0&
1%
#40
0"
0(
1!
1&
0%
0$
1#
#50
1"
1(
0!
0&
1%
#60
0(
1)
0'
0%
1$
#70
1!
1&
1%
