myproject/wallace/wallace.v
/*module wallace(

input	wire	[3:0]	A, B, // Input Data
output	wire	[7:0]	prod;

);

	wire	[11:0]	s,c;

endmodule
//////////////////////////////////////
*/
module ha( //Half Adder

input	A, B, // Input Data
output	S, C //S is Sum, C is Carry
);

assign	C = A & B; // AND operation
assign	S = ~(A | B); // XOR operation

endmodule

////////////////////////////

module fa( //Full Adder

input	A, B, Cin, // Input Data
output	S, C

);


	wire	S1,S2,C1,C2;
	wire	Data_Sum, Data_Carry;
// instantiation
ha	ha1(
	.A(A),
	.B(B), 
	.S(S1), 
	.C(C1));
ha	ha2(
	.A(Cin), 
	.B(S1), 
	.S(S2), 
	.C(C2));


assign	Data_Sum = S2;
assign	Data_Carry = C1 | C2;

endmodule


///////////////////////////////////
module TB;

reg	A,B,C;
wire	Data_Sum, Data_Carry;

fa	u0(
	.A(A), 
	.B(B), 
	.Cin(C), 
	.S(Data_Sum), 
	.C(Data_Carry));


initial begin


	A = 0; B = 0; C = 0; #10;
	A = 0; B = 0; C = 1; #10;
	A = 0; B = 1; C = 0; #10;
	A = 0; B = 1; C = 1; #10;
	A = 1; B = 0; C = 0; #10;
	A = 1; B = 0; C = 1; #10;
	A = 1; B = 1; C = 0; #10;
	A = 1; B = 1; C = 1; #10;
end

initial	begin
$monitor("%b	|	%b	|	%b	|	%b	|	%b",
	A,B,C,Data_Sum,Data_Carry);
end

initial begin

	$dumpfile("FA.vcd");
	$dumpvars;
	#100
	$finish;
	end



endmodule

myproject/wallace/FA.vcd
$date
	Wed Jul  5 13:11:06 2023
$end
$version
	Icarus Verilog
$end
$timescale
	1s
$end
$scope module TB $end
$var wire 1 ! Data_Carry $end
$var wire 1 " Data_Sum $end
$var reg 1 # A $end
$var reg 1 $ B $end
$var reg 1 % C $end
$scope module u0 $end
$var wire 1 # A $end
$var wire 1 $ B $end
$var wire 1 ! C $end
$var wire 1 % Cin $end
$var wire 1 & Data_Carry $end
$var wire 1 ' Data_Sum $end
$var wire 1 " S $end
$var wire 1 ( S2 $end
$var wire 1 ) S1 $end
$var wire 1 * C2 $end
$var wire 1 + C1 $end
$scope module ha1 $end
$var wire 1 # A $end
$var wire 1 $ B $end
$var wire 1 + C $end
$var wire 1 ) S $end
$upscope $end
$scope module ha2 $end
$var wire 1 % A $end
$var wire 1 ) B $end
$var wire 1 * C $end
$var wire 1 ( S $end
$upscope $end
$upscope $end
$upscope $end
$enddefinitions $end
#0
$dumpvars
0+
0*
1)
0(
0'
0&
0%
0$
0#
z"
z!
$end
#10
1&
1*
1%
#20
1'
1(
0&
0)
0*
0%
1$
#30
0'
0(
1%
#40
1'
1(
0%
0$
1#
#50
0'
0(
1%
#60
1'
1(
1&
1+
0%
1$
#70
0'
0(
1%
