myproject/wallace/fulladder.v
module half_adder(
    Data_in_A,
    Data_in_B,
    Data_out_Sum,
    Data_out_Carry
    );

    //what are the input ports.
    input Data_in_A;
    input Data_in_B;
    //What are the output ports.
    output Data_out_Sum;
     output Data_out_Carry;
     
     //Implement the Sum and Carry equations using Verilog Bit operators.
     assign Data_out_Sum = Data_in_A ^ Data_in_B;  //XOR operation
     assign Data_out_Carry = Data_in_A & Data_in_B; //AND operation
    
endmodule


module full_adder(
    Data_in_A,  //input A
    Data_in_B,  //input B
    Data_in_C,  //input C
     Data_out_Sum,
     Data_out_Carry
    );

    //what are the input ports.
    input Data_in_A;
    input Data_in_B;
     input Data_in_C;
    //What are the output ports.
    output Data_out_Sum;
     output Data_out_Carry;
     //Internal variables
     wire ha1_sum;
     wire ha2_sum;
     wire ha1_carry;
     wire ha2_carry;
     wire Data_out_Sum;
     wire Data_out_Carry;

     //Instantiate the half adder 1
    half_adder  ha1(
        .Data_in_A(Data_in_A),
        .Data_in_B(Data_in_B),
        .Data_out_Sum(ha1_sum),
        .Data_out_Carry(ha1_carry)
    );
    
    //Instantiate the half adder 2
    half_adder  ha2(
        .Data_in_A(Data_in_C),
        .Data_in_B(ha1_sum),
        .Data_out_Sum(ha2_sum),
        .Data_out_Carry(ha2_carry)
    );

    //sum output from 2nd half adder is connected to full adder output
    assign Data_out_Sum = ha2_sum;  
    //The carry's from both the half adders are OR'ed to get the final carry./
    assign Data_out_Carry = ha1_carry | ha2_carry;
    
endmodule

module tb_fullAdd;

    // Inputs
    reg Data_in_A;
    reg Data_in_B;
    reg Data_in_C;

    // Outputs
    wire Data_out_Sum;
    wire Data_out_Carry;

    // Instantiate the Unit Under Test (UUT)
    full_adder uut (
        .Data_in_A(Data_in_A), 
        .Data_in_B(Data_in_B), 
        .Data_in_C(Data_in_C), 
        .Data_out_Sum(Data_out_Sum), 
        .Data_out_Carry(Data_out_Carry)
    );

    initial begin
        //Apply inputs. 8 combinations of inputs are possible.
        //They are given below.
        Data_in_A = 0;  Data_in_B = 0;  Data_in_C = 0;  #100;
        Data_in_A = 0;  Data_in_B = 0;  Data_in_C = 1;  #100;
        Data_in_A = 0;  Data_in_B = 1;  Data_in_C = 0;  #100;
        Data_in_A = 0;  Data_in_B = 1;  Data_in_C = 1;  #100;
        Data_in_A = 1;  Data_in_B = 0;  Data_in_C = 0;  #100;
        Data_in_A = 1;  Data_in_B = 0;  Data_in_C = 1;  #100;
        Data_in_A = 1;  Data_in_B = 1;  Data_in_C = 0;  #100;
        Data_in_A = 1;  Data_in_B = 1;  Data_in_C = 1;  #100;
    end
     
	initial begin
$display("%d	%d	%d	%d	%d",Data_in_A,Data_in_B,Data_in_C,Data_out_Sum,Data_out_Carry);
	end

	initial begin
	$dumpfile("tb.vcd");
	$dumpvars;
	end

	initial	begin
	#1000
	$finish;
	
	end


 
endmodule

myproject/wallace/tb.vcd
$date
	Wed Jul  5 12:53:09 2023
$end
$version
	Icarus Verilog
$end
$timescale
	1s
$end
$scope module tb_fullAdd $end
$var wire 1 ! Data_out_Sum $end
$var wire 1 " Data_out_Carry $end
$var reg 1 # Data_in_A $end
$var reg 1 $ Data_in_B $end
$var reg 1 % Data_in_C $end
$scope module uut $end
$var wire 1 # Data_in_A $end
$var wire 1 $ Data_in_B $end
$var wire 1 % Data_in_C $end
$var wire 1 " Data_out_Carry $end
$var wire 1 ! Data_out_Sum $end
$var wire 1 & ha2_sum $end
$var wire 1 ' ha2_carry $end
$var wire 1 ( ha1_sum $end
$var wire 1 ) ha1_carry $end
$scope module ha1 $end
$var wire 1 # Data_in_A $end
$var wire 1 $ Data_in_B $end
$var wire 1 ) Data_out_Carry $end
$var wire 1 ( Data_out_Sum $end
$upscope $end
$scope module ha2 $end
$var wire 1 % Data_in_A $end
$var wire 1 ( Data_in_B $end
$var wire 1 ' Data_out_Carry $end
$var wire 1 & Data_out_Sum $end
$upscope $end
$upscope $end
$upscope $end
$enddefinitions $end
#0
$dumpvars
0)
0(
0'
0&
0%
0$
0#
0"
0!
$end
#100
1!
1&
1%
#200
1(
0%
1$
#300
1"
0!
0&
1'
1%
#400
0"
1!
1&
0'
0%
0$
1#
#500
1"
0!
0&
1'
1%
#600
0'
0(
1)
0%
1$
#700
1!
1&
1%
